linalgpy/__init__.py
linalgpy/core/__init__.py
linalgpy/core/matrixexpression.py
linalgpy/core/solver.py
linalgpy/determinant/__init__.py
linalgpy/determinant/course.py
linalgpy/determinant/determinant.py
linalgpy/determinant/laplaceexpand.py
linalgpy/eigen/__init__.py
linalgpy/eigen/diagnoalize.py
linalgpy/eigen/eigen.py
linalgpy/eigen/eigenvalue.py
linalgpy/latex/__init__.py
linalgpy/latex/latextrans.py
linalgpy/latex/parser.py
linalgpy/linequ/__init__.py
linalgpy/linequ/gausslimination.py
linalgpy/linequ/inverse.py
linalgpy/linequ/lambdalinequ.py
linalgpy/linequ/linequsolver.py
linalgpy/linspace/MLIG.py
linalgpy/linspace/__init__.py
linalgpy/linspace/lincombination.py
linalgpy/linspace/linspace.py
linalgpy/metric/__init__.py
linalgpy/metric/metricbase.py
linalgpy/metric/schmidt.py
linalgpy/mnmatrix/__init__.py
linalgpy/mnmatrix/cornermatrix.py
linalgpy/mnmatrix/eletran.py
linalgpy/mnmatrix/lammatrix.py
linalgpy/mnmatrix/mnmatrix.py
linalgpy/poly/__init__.py
linalgpy/poly/poly.py
linalgpy/quad/__init__.py
linalgpy/quad/quadbase.py
linalgpy/quad/quadratic.py
linalgpy-0.0.3.dist-info/METADATA
linalgpy-0.0.3.dist-info/WHEEL
linalgpy-0.0.3.dist-info/top_level.txt
linalgpy-0.0.3.dist-info/RECORD
