Metadata-Version: 2.1
Name: linalgpy
Version: 0.0.3
Summary: example package of linalgpy
Home-page: https://github.com/HelloMrGeorge/LinearAlgebraMachine
Author: hellomrgeorge
Author-email: hellomrgeorge@outlook.com
License: MIT license
Project-URL: Bug Tracker, https://github.com/HelloMrGeorge/LinearAlgebraMachine/issues
Platform: UNKNOWN
Classifier: Programming Language :: Python :: 3
Classifier: License :: OSI Approved :: MIT License
Classifier: Operating System :: OS Independent
Requires-Python: >=3.6
Requires-Dist: sympy (>=1.8)
Requires-Dist: antlr4-python3-runtime (==4.7.2)
